scietex/hal/qcm/__init__.py
scietex/hal/qcm/py.typed
scietex/hal/qcm/version.py
scietex/hal/qcm/base/__init__.py
scietex/hal/qcm/base/data.py
scietex/hal/qcm/base/ftm_calculation.py
scietex/hal/qcm/base/ftm_materials_data.py
scietex/hal/qcm/base/gated_ftm.py
scietex/hal/qcm/base/rs485/__init__.py
scietex/hal/qcm/base/rs485/gated_ftm.py
scietex/hal/qcm/base/serial/__init__.py
scietex/hal/qcm/base/serial/gated_ftm.py
scietex/hal/qcm/cyky/__init__.py
scietex/hal/qcm/cyky/tm106b.py
scietex/hal/qcm/scietex/__init__.py
scietex/hal/qcm/scietex/ftm_one.py
scietex/hal/qcm/scietex/ftm_one_usb.py
scietex/hal/qcm/scietex/utils.py
scietex_hal_qcm-1.1.0.dist-info/licenses/LICENSE
scietex_hal_qcm-1.1.0.dist-info/METADATA
scietex_hal_qcm-1.1.0.dist-info/WHEEL
scietex_hal_qcm-1.1.0.dist-info/top_level.txt
scietex_hal_qcm-1.1.0.dist-info/RECORD
